[
    {
        "name": "Qwerf",
        "data": {
            "roll": 0.41702479338842974,
            "alternate": 0.2188783943329398,
            "redirect": 0.1893624557260921,
            "onehand": 0.0590318772136954,
            "sfb": 0.11570247933884298
        }
    },
    {
        "name": "Qwerty",
        "data": {
            "roll": 0.41938606847697757,
            "alternate": 0.2188783943329398,
            "redirect": 0.18700118063754428,
            "onehand": 0.06139315230224321,
            "sfb": 0.11334120425029516
        }
    },
    {
        "name": "Halmak",
        "data": {
            "roll": 0.4280519480519481,
            "alternate": 0.37865407319952776,
            "redirect": 0.09884297520661157,
            "onehand": 0.02715466351829988,
            "sfb": 0.06729634002361275
        }
    },
    {
        "name": "QGMLWY",
        "data": {
            "roll": 0.42880755608028337,
            "alternate": 0.3345926800472255,
            "redirect": 0.10791027154663518,
            "onehand": 0.018890200708382526,
            "sfb": 0.10979929161747344
        }
    },
    {
        "name": "klauser",
        "data": {
            "roll": 0.4328571428571429,
            "alternate": 0.4110802833530106,
            "redirect": 0.05925029515938607,
            "onehand": 0.024793388429752067,
            "sfb": 0.07201889020070838
        }
    },
    {
        "name": "Dvorak",
        "data": {
            "roll": 0.4335419126328217,
            "alternate": 0.42372491145218416,
            "redirect": 0.04710153482880756,
            "onehand": 0.015348288075560802,
            "sfb": 0.08028335301062574
        }
    },
    {
        "name": "Optimal-trigram",
        "data": {
            "roll": 0.4367650531286895,
            "alternate": 0.4038134592680047,
            "redirect": 0.08149940968122786,
            "onehand": 0.020070838252656435,
            "sfb": 0.05785123966942149
        }
    },
    {
        "name": "Capewell-Dvorak",
        "data": {
            "roll": 0.4370484061393152,
            "alternate": 0.388913813459268,
            "redirect": 0.06541912632821724,
            "onehand": 0.012987012987012988,
            "sfb": 0.09563164108618655
        }
    },
    {
        "name": "Beakl-15",
        "data": {
            "roll": 0.43853600944510035,
            "alternate": 0.41414403778040143,
            "redirect": 0.04696576151121606,
            "onehand": 0.015348288075560802,
            "sfb": 0.08500590318772137
        }
    },
    {
        "name": "kaehi",
        "data": {
            "roll": 0.4409445100354191,
            "alternate": 0.3391499409681228,
            "redirect": 0.09239669421487604,
            "onehand": 0.0448642266824085,
            "sfb": 0.08264462809917356
        }
    },
    {
        "name": "Norman",
        "data": {
            "roll": 0.4424911452184179,
            "alternate": 0.22680637544273907,
            "redirect": 0.16305194805194806,
            "onehand": 0.05430932703659976,
            "sfb": 0.11334120425029516
        }
    },
    {
        "name": "Optimal-Digram",
        "data": {
            "roll": 0.4427508854781582,
            "alternate": 0.4285655253837072,
            "redirect": 0.05784533648170012,
            "onehand": 0.015348288075560802,
            "sfb": 0.05548996458087367
        }
    },
    {
        "name": "ADNW-english-bigram",
        "data": {
            "roll": 0.4427508854781582,
            "alternate": 0.4285655253837072,
            "redirect": 0.05784533648170012,
            "onehand": 0.015348288075560802,
            "sfb": 0.05548996458087367
        }
    },
    {
        "name": "Oneproduct",
        "data": {
            "roll": 0.443258559622196,
            "alternate": 0.3362219598583235,
            "redirect": 0.10835891381345927,
            "onehand": 0.0448642266824085,
            "sfb": 0.06729634002361275
        }
    },
    {
        "name": "Engram",
        "data": {
            "roll": 0.44344746162927984,
            "alternate": 0.39929161747343567,
            "redirect": 0.06989374262101535,
            "onehand": 0.021251475796930343,
            "sfb": 0.06611570247933884
        }
    },
    {
        "name": "Colman",
        "data": {
            "roll": 0.4453364817001181,
            "alternate": 0.37001180637544273,
            "redirect": 0.09964580873671783,
            "onehand": 0.024793388429752067,
            "sfb": 0.0602125147579693
        }
    },
    {
        "name": "Three",
        "data": {
            "roll": 0.4514285714285714,
            "alternate": 0.3510271546635183,
            "redirect": 0.06295159386068477,
            "onehand": 0.02715466351829988,
            "sfb": 0.10743801652892562
        }
    },
    {
        "name": "Beakl-19",
        "data": {
            "roll": 0.45152302243211334,
            "alternate": 0.41414403778040143,
            "redirect": 0.04342384887839433,
            "onehand": 0.020070838252656435,
            "sfb": 0.07083825265643448
        }
    },
    {
        "name": "Uciea",
        "data": {
            "roll": 0.45185360094451005,
            "alternate": 0.41988193624557263,
            "redirect": 0.06214876033057851,
            "onehand": 0.011806375442739079,
            "sfb": 0.05430932703659976
        }
    },
    {
        "name": "Beakl-19-bis",
        "data": {
            "roll": 0.4545100354191263,
            "alternate": 0.4220956316410862,
            "redirect": 0.03956906729634002,
            "onehand": 0.014167650531286895,
            "sfb": 0.06965761511216056
        }
    },
    {
        "name": "Semimak",
        "data": {
            "roll": 0.45720188902007086,
            "alternate": 0.36585005903187723,
            "redirect": 0.08840023612750886,
            "onehand": 0.03423848878394333,
            "sfb": 0.05430932703659976
        }
    },
    {
        "name": "Niro",
        "data": {
            "roll": 0.4578512396694215,
            "alternate": 0.25218417945690674,
            "redirect": 0.1565525383707202,
            "onehand": 0.0590318772136954,
            "sfb": 0.0743801652892562
        }
    },
    {
        "name": "Hands-Down",
        "data": {
            "roll": 0.45985832349468714,
            "alternate": 0.32615112160566706,
            "redirect": 0.10537190082644628,
            "onehand": 0.05194805194805195,
            "sfb": 0.05667060212514758
        }
    },
    {
        "name": "Balance-12",
        "data": {
            "roll": 0.4609681227863046,
            "alternate": 0.3055253837072019,
            "redirect": 0.12370720188902007,
            "onehand": 0.0448642266824085,
            "sfb": 0.06493506493506493
        }
    },
    {
        "name": "boo",
        "data": {
            "roll": 0.46140495867768594,
            "alternate": 0.3312809917355372,
            "redirect": 0.12939197166469893,
            "onehand": 0.020070838252656435,
            "sfb": 0.05785123966942149
        }
    },
    {
        "name": "Mtgap",
        "data": {
            "roll": 0.4627508854781582,
            "alternate": 0.370159386068477,
            "redirect": 0.08798701298701299,
            "onehand": 0.01770956316410862,
            "sfb": 0.06139315230224321
        }
    },
    {
        "name": "Capewell",
        "data": {
            "roll": 0.4646517119244392,
            "alternate": 0.22576151121605667,
            "redirect": 0.1856198347107438,
            "onehand": 0.0602125147579693,
            "sfb": 0.06375442739079103
        }
    },
    {
        "name": "Minimak-12",
        "data": {
            "roll": 0.4665289256198347,
            "alternate": 0.30156434474616295,
            "redirect": 0.10557851239669422,
            "onehand": 0.03659976387249114,
            "sfb": 0.089728453364817
        }
    },
    {
        "name": "Asset",
        "data": {
            "roll": 0.4672018890200708,
            "alternate": 0.2368831168831169,
            "redirect": 0.15778040141676505,
            "onehand": 0.05548996458087367,
            "sfb": 0.08264462809917356
        }
    },
    {
        "name": "White",
        "data": {
            "roll": 0.4684297520661157,
            "alternate": 0.18727272727272729,
            "redirect": 0.16247933884297522,
            "onehand": 0.05430932703659976,
            "sfb": 0.12750885478158205
        }
    },
    {
        "name": "Hieamtsrn",
        "data": {
            "roll": 0.4685478158205431,
            "alternate": 0.4062219598583235,
            "redirect": 0.04258559622195986,
            "onehand": 0.020070838252656435,
            "sfb": 0.06257378984651712
        }
    },
    {
        "name": "Colemak-Qi-x",
        "data": {
            "roll": 0.4689374262101535,
            "alternate": 0.3098051948051948,
            "redirect": 0.11145808736717827,
            "onehand": 0.05430932703659976,
            "sfb": 0.05548996458087367
        }
    },
    {
        "name": "Colemak-Qi",
        "data": {
            "roll": 0.4689374262101535,
            "alternate": 0.3098051948051948,
            "redirect": 0.11145808736717827,
            "onehand": 0.05430932703659976,
            "sfb": 0.05548996458087367
        }
    },
    {
        "name": "Rolll",
        "data": {
            "roll": 0.4690436835891381,
            "alternate": 0.32037780401416766,
            "redirect": 0.10668240850059033,
            "onehand": 0.043683589138134596,
            "sfb": 0.0602125147579693
        }
    },
    {
        "name": "Dwarf",
        "data": {
            "roll": 0.4695395513577332,
            "alternate": 0.3283943329397875,
            "redirect": 0.09817001180637544,
            "onehand": 0.047225501770956316,
            "sfb": 0.05667060212514758
        }
    },
    {
        "name": "Workman",
        "data": {
            "roll": 0.47331759149940966,
            "alternate": 0.28754427390791026,
            "redirect": 0.11871310507674145,
            "onehand": 0.03896103896103896,
            "sfb": 0.08146399055489964
        }
    },
    {
        "name": "Ctgap",
        "data": {
            "roll": 0.4733766233766234,
            "alternate": 0.31939197166469896,
            "redirect": 0.10097402597402598,
            "onehand": 0.043683589138134596,
            "sfb": 0.06257378984651712
        }
    },
    {
        "name": "Qwpr",
        "data": {
            "roll": 0.4737308146399056,
            "alternate": 0.3015053128689492,
            "redirect": 0.10551948051948051,
            "onehand": 0.02715466351829988,
            "sfb": 0.09208972845336481
        }
    },
    {
        "name": "Arensito",
        "data": {
            "roll": 0.4802597402597403,
            "alternate": 0.2504250295159386,
            "redirect": 0.15243211334120424,
            "onehand": 0.0590318772136954,
            "sfb": 0.05785123966942149
        }
    },
    {
        "name": "SIND",
        "data": {
            "roll": 0.4810153482880756,
            "alternate": 0.2470956316410862,
            "redirect": 0.159728453364817,
            "onehand": 0.05785123966942149,
            "sfb": 0.05430932703659976
        }
    },
    {
        "name": "ISRT",
        "data": {
            "roll": 0.4821133412042503,
            "alternate": 0.308530106257379,
            "redirect": 0.1172668240850059,
            "onehand": 0.03541912632821724,
            "sfb": 0.05667060212514758
        }
    },
    {
        "name": "Whorf",
        "data": {
            "roll": 0.4826800472255018,
            "alternate": 0.29939197166469894,
            "redirect": 0.11048996458087368,
            "onehand": 0.053128689492325853,
            "sfb": 0.05430932703659976
        }
    },
    {
        "name": "Dvormax",
        "data": {
            "roll": 0.48334120425029514,
            "alternate": 0.36458677685950414,
            "redirect": 0.07769185360094451,
            "onehand": 0.018890200708382526,
            "sfb": 0.05548996458087367
        }
    },
    {
        "name": "Real",
        "data": {
            "roll": 0.4875442739079103,
            "alternate": 0.33533057851239667,
            "redirect": 0.08975796930342385,
            "onehand": 0.0295159386068477,
            "sfb": 0.05785123966942149
        }
    },
    {
        "name": "APT",
        "data": {
            "roll": 0.48760330578512395,
            "alternate": 0.31345926800472257,
            "redirect": 0.10566706021251476,
            "onehand": 0.03423848878394333,
            "sfb": 0.0590318772136954
        }
    },
    {
        "name": "Heart",
        "data": {
            "roll": 0.48760330578512395,
            "alternate": 0.31345926800472257,
            "redirect": 0.10920897284533648,
            "onehand": 0.03305785123966942,
            "sfb": 0.05667060212514758
        }
    },
    {
        "name": "RTNA",
        "data": {
            "roll": 0.4881227863046045,
            "alternate": 0.26892561983471075,
            "redirect": 0.14731995277449822,
            "onehand": 0.03896103896103896,
            "sfb": 0.05667060212514758
        }
    },
    {
        "name": "FLAW",
        "data": {
            "roll": 0.4881227863046045,
            "alternate": 0.28191263282172374,
            "redirect": 0.11780401416765053,
            "onehand": 0.05548996458087367,
            "sfb": 0.05667060212514758
        }
    },
    {
        "name": "Typehack",
        "data": {
            "roll": 0.488642266824085,
            "alternate": 0.27220779220779223,
            "redirect": 0.1222668240850059,
            "onehand": 0.05785123966942149,
            "sfb": 0.0590318772136954
        }
    },
    {
        "name": "The-1",
        "data": {
            "roll": 0.4912987012987013,
            "alternate": 0.2372314049586777,
            "redirect": 0.13923848878394332,
            "onehand": 0.06493506493506493,
            "sfb": 0.06729634002361275
        }
    },
    {
        "name": "Pine",
        "data": {
            "roll": 0.4918772136953955,
            "alternate": 0.29125147579693034,
            "redirect": 0.1058913813459268,
            "onehand": 0.049586776859504134,
            "sfb": 0.06139315230224321
        }
    },
    {
        "name": "Soul",
        "data": {
            "roll": 0.49493506493506495,
            "alternate": 0.2891322314049587,
            "redirect": 0.10731404958677686,
            "onehand": 0.04604486422668241,
            "sfb": 0.06257378984651712
        }
    },
    {
        "name": "Colemak",
        "data": {
            "roll": 0.4985242030696576,
            "alternate": 0.3015053128689492,
            "redirect": 0.10551948051948051,
            "onehand": 0.03659976387249114,
            "sfb": 0.05785123966942149
        }
    },
    {
        "name": "Colemak-DH",
        "data": {
            "roll": 0.4985242030696576,
            "alternate": 0.3015053128689492,
            "redirect": 0.10551948051948051,
            "onehand": 0.03659976387249114,
            "sfb": 0.05785123966942149
        }
    },
    {
        "name": "ColemaQ-F",
        "data": {
            "roll": 0.5043211334120425,
            "alternate": 0.27499409681227865,
            "redirect": 0.1226918536009445,
            "onehand": 0.04132231404958678,
            "sfb": 0.05667060212514758
        }
    },
    {
        "name": "ColemaQ",
        "data": {
            "roll": 0.5055017709563164,
            "alternate": 0.27499409681227865,
            "redirect": 0.1226918536009445,
            "onehand": 0.04250295159386069,
            "sfb": 0.05430932703659976
        }
    },
    {
        "name": "Rsi-terminated",
        "data": {
            "roll": 0.5146162927981109,
            "alternate": 0.261582054309327,
            "redirect": 0.13525383707201888,
            "onehand": 0.03305785123966942,
            "sfb": 0.05548996458087367
        }
    },
    {
        "name": "stndc",
        "data": {
            "roll": 0.5200236127508855,
            "alternate": 0.2600590318772137,
            "redirect": 0.127827626918536,
            "onehand": 0.03659976387249114,
            "sfb": 0.05548996458087367
        }
    }
]